pycnv/VERSION
pycnv/__init__.py
pycnv/pycnv.py
pycnv/pycnv_obsolete.py
pycnv/pycnv_sum_folder.py
pycnv/rules/standard_names.yaml
pycnv/stations/iow_stations.yaml
pycnv-0.4.1.dist-info/LICENSE
pycnv-0.4.1.dist-info/METADATA
pycnv-0.4.1.dist-info/WHEEL
pycnv-0.4.1.dist-info/entry_points.txt
pycnv-0.4.1.dist-info/top_level.txt
pycnv-0.4.1.dist-info/RECORD
